kusanagi/__init__.py
kusanagi/args.py
kusanagi/defaults.py
kusanagi/core/__init__.py
kusanagi/core/filter/__init__.py
kusanagi/core/helper/__init__.py
kusanagi/core/loader/__init__.py
kusanagi/core/loader/template/__init__.py
kusanagi/core/loader/yaml/__init__.py
kusanagi/core/loader/yaml/loader.py
kusanagi/core/loader/yaml/validator.py
kusanagi/core/output/__init__.py
kusanagi/core/output/clipboard/__init__.py
kusanagi/core/output/encoder/__init__.py
kusanagi/core/output/printer/__init__.py
kusanagi/core/parser/__init__.py
kusanagi/core/parser/function.py
kusanagi/core/payload/__init__.py
kusanagi/core/payload/cmd/__init__.py
kusanagi/core/payload/cmd/obfuscator/__init__.py
kusanagi/core/payload/cmd/obfuscator/validator.py
kusanagi/core/payload/cmd/revshell/__init__.py
kusanagi/core/payload/cmd/revshell/validator.py
kusanagi/core/payload/code/__init__.py
kusanagi/core/payload/code/obfuscator/__init__.py
kusanagi/core/payload/code/obfuscator/validator.py
kusanagi/core/payload/code/revshell/__init__.py
kusanagi/core/payload/code/revshell/validator.py
kusanagi/core/sorter/__init__.py
kusanagi/files/cmd/obfuscators/bash-gnu.yml
kusanagi/files/cmd/revshells/bash.yml
kusanagi/files/code/obfuscators/bash.yml
kusanagi/files/code/obfuscators/php.yml
kusanagi/files/code/obfuscators/python.yml
kusanagi/files/code/revshells/bash.yml
kusanagi/files/code/revshells/php.yml
kusanagi/files/code/revshells/python.yml
kusanagi/files/code/revshells/ruby.yml
kusanagi-0.0.5.dist-info/LICENSE.txt
kusanagi-0.0.5.dist-info/METADATA
kusanagi-0.0.5.dist-info/WHEEL
kusanagi-0.0.5.dist-info/entry_points.txt
kusanagi-0.0.5.dist-info/top_level.txt
kusanagi-0.0.5.dist-info/RECORD
