Metadata-Version: 2.1
Name: kusanagi
Version: 0.0.5
Summary: Kusanagi is a bind and reverse shell payload generator with obfuscation and badchar support.
Home-page: https://github.com/cytopia/kusanagi
Author: cytopia
Author-email: cytopia@everythingcli.org
License: MIT
Project-URL: Source Code, https://github.com/cytopia/kusanagi
Project-URL: Bug Tracker, https://github.com/cytopia/kusanagi/issues
Keywords: payload,bind shell,reverse shell,generator,shell,kusanagi
Platform: UNKNOWN
Classifier: Development Status :: 3 - Alpha
Classifier: Environment :: Console
Classifier: Intended Audience :: Developers
Classifier: Intended Audience :: Information Technology
Classifier: Intended Audience :: Science/Research
Classifier: Intended Audience :: System Administrators
Classifier: License :: OSI Approved :: MIT License
Classifier: Operating System :: OS Independent
Classifier: Programming Language :: Python :: 3 :: Only
Classifier: Programming Language :: Python :: 3.6
Classifier: Programming Language :: Python :: 3.7
Classifier: Programming Language :: Python :: 3.8
Classifier: Programming Language :: Python :: 3.9
Classifier: Programming Language :: Python :: Implementation :: CPython
Classifier: Programming Language :: Python :: Implementation :: PyPy
Classifier: Topic :: Internet
Classifier: Topic :: Security
Classifier: Topic :: System :: Shells
Classifier: Topic :: System :: Systems Administration
Classifier: Topic :: Terminals
Classifier: Topic :: Utilities
Classifier: Typing :: Typed
Requires-Python: >=3.6
Requires-Dist: PyYAML
Requires-Dist: pyperclip (>=1.8.2)
Requires-Dist: termcolor (>=1.1.0)
